sondera/__init__.py
sondera/datatypes.py
sondera/exceptions.py
sondera/geo_utils.py
sondera/clients/__init__.py
sondera/clients/parameters.py
sondera/clients/sgu/__init__.py
sondera/clients/sgu/groundwater.py
sondera/clients/smhi/__init__.py
sondera/clients/smhi/common.py
sondera/clients/smhi/hydroobs.py
sondera/clients/smhi/metobs.py
sondera/clients/smhi/radar.py
sondera/clients/smhi/smhistrang.py
sondera-0.0.4.dist-info/LICENSE
sondera-0.0.4.dist-info/METADATA
sondera-0.0.4.dist-info/WHEEL
sondera-0.0.4.dist-info/top_level.txt
sondera-0.0.4.dist-info/RECORD
