Metadata-Version: 2.1
Name: sondera
Version: 0.0.4
Summary: Python client for accessing Swedish hydrology and meteorology related open data and observations, including SMHI and SGU open data API.
Home-page: https://github.com/rhkarls/sondera
License: MIT
Project-URL: Bug Tracker, https://github.com/rhkarls/sondera/issues
Classifier: Development Status :: 2 - Pre-Alpha
Classifier: License :: OSI Approved :: MIT License
Classifier: Programming Language :: Python :: 3
Classifier: Programming Language :: Python :: 3.8
Classifier: Programming Language :: Python :: 3.9
Classifier: Programming Language :: Python :: 3.10
Requires-Python: >=3.8
License-File: LICENSE
Requires-Dist: numpy
Requires-Dist: pandas
Requires-Dist: geopandas
Requires-Dist: requests
Requires-Dist: tqdm
Provides-Extra: test
Requires-Dist: pytest ; extra == 'test'
